Metadata-Version: 1.0
Name: haetek-demo
Version: 1.0.0
Summary: Haetek Algorithm Platform
Home-page: https://haetek.com/
Author: haetek_shenzhen
Author-email: haetek123@163.com
License: UNKNOWN
Platform: UNKNOWN
